BeautifulUI/__init__.py
BeautifulUI/CLI/__init__.py
BeautifulUI/CLI/manage.py
BeautifulUI/CLI/Build/__init__.py
BeautifulUI/CLI/Build/app.py
BeautifulUI/CLI/Describe/__init__.py
BeautifulUI/CLI/Describe/function.py
BeautifulUI/DSL/__init__.py
BeautifulUI/GUI/__init__.py
BeautifulUI-1.0.2.data/scripts/entry.py
PyUi/__init__.py
PyUi/CLI/__init__.py
PyUi/CLI/manage.py
PyUi/CLI/Build/__init__.py
PyUi/CLI/Describe/__init__.py
PyUi/CLI/Describe/function.py
BeautifulUI-1.0.2.dist-info/LICENSE
BeautifulUI-1.0.2.dist-info/METADATA
BeautifulUI-1.0.2.dist-info/WHEEL
BeautifulUI-1.0.2.dist-info/top_level.txt
BeautifulUI-1.0.2.dist-info/zip-safe
BeautifulUI-1.0.2.dist-info/RECORD
